<?xml version="1.0" encoding="utf-8"?>
<Unit name="Blade" level="80" rank="2">
    <Stats hp="2628.36" atk="1125.4319999999998" def="815.85" spd="97" crit_rate="0.05" crit_dmg="0.5"
           hp_prc="1.4440000000000004" crit_rate_prc="0.7364000027999998" effect_res_prc="0.1864000052"
           hp_fix="705.5999999999999" crit_dmg_prc="1.1404800048" break_dmg_prc="0.18144000159999998"
           atk_fix="390.90379199999995" def_prc="0.1836" spd_fix="24.5" effect_hit_prc="0.2419200144"
           wind_dmg_prc="0.388803015" atk_prc="0.1080000063"/>
    <LightCone rank="1" level="80" name="The Unreachable Side"/>
    <Skill name="Shard Sword" level="6" max_level="9"/>
    <Skill name="Hellscape" level="10" max_level="15"/>
    <Skill name="Death Sentence" level="10" max_level="15"/>
    <Skill name="Shuhu's Gift" level="10" max_level="15"/>
    <Skill name="120506" level="0" max_level="1"/>
    <Skill name="Karma Wind" level="1" max_level="1"/>
    <Skill name="Forest of Swords" level="6" max_level="9"/>
    <RelicSet name="Longevous Disciple" num="4"/>
    <RelicSet name="Inert Salsotto" num="2"/>
</Unit>